simbio/__init__.py
simbio/core.py
simbio/test_core.py
simbio/io/biomodels.py
simbio/io/mathML/__init__.py
simbio/io/mathML/exporter.py
simbio/io/mathML/importer.py
simbio/io/mathML/symbol.py
simbio/io/mathML/test_mathML.py
simbio/io/mathML/to_symbolite.py
simbio/io/sbml/__init__.py
simbio/io/sbml/from_libsbml.py
simbio/io/sbml/importer.py
simbio/io/sbml/test_importer.py
simbio/io/sbml/types.py
simbio/io/sbml/tests/atol_factor.csv
simbio/io/sbml/tests/test_sbml_test_suite.py
simbio/reactions/__init__.py
simbio/reactions/compound.py
simbio/reactions/enzymatic.py
simbio/reactions/single.py
simbio/reactions/test_reactions.py
SimBio-0.4.0.dist-info/METADATA
SimBio-0.4.0.dist-info/WHEEL
SimBio-0.4.0.dist-info/top_level.txt
SimBio-0.4.0.dist-info/RECORD
