Metadata-Version: 2.1
Name: SimBio
Version: 0.4.0
Summary: Simulation of Biological Systems
Author-email: "Hernán E. Grecco" <hernan.grecco@gmail.com>, Mauro Silberberg <maurosilber@gmail.com>
Project-URL: Homepage, https://github.com/hgrecco/simbio
Project-URL: Bug Tracker, https://github.com/hgrecco/simbio/issues
Keywords: mass action,michaelis menten,ode,compartment,reaction,SBML,poincare
Classifier: Intended Audience :: Developers
Classifier: Intended Audience :: Science/Research
Classifier: Topic :: Scientific/Engineering
Classifier: Topic :: Software Development :: Libraries
Classifier: Programming Language :: Python :: 3
Classifier: License :: OSI Approved :: BSD License
Classifier: Operating System :: OS Independent
Requires-Python: >=3.10
Requires-Dist: poincare >=0.3.1
Provides-Extra: docs
Requires-Dist: jupyter-book ; extra == 'docs'
Requires-Dist: jupytext ; extra == 'docs'
Requires-Dist: numba ; extra == 'docs'
Requires-Dist: simbio-corbat2018 ; extra == 'docs'
Requires-Dist: simbio[test] ; extra == 'docs'
Provides-Extra: io
Requires-Dist: biomodels ; extra == 'io'
Requires-Dist: python-libsbml ; extra == 'io'
Provides-Extra: test
Requires-Dist: pooch ; extra == 'test'
Requires-Dist: pytest <8.1 ; extra == 'test'
Requires-Dist: simbio[io] ; extra == 'test'
